ffc_mkdocs_video/__init__.py
ffc_mkdocs_video/plugin.py
ffc_mkdocs_video-1.0.1.dist-info/LICENSE
ffc_mkdocs_video-1.0.1.dist-info/METADATA
ffc_mkdocs_video-1.0.1.dist-info/WHEEL
ffc_mkdocs_video-1.0.1.dist-info/entry_points.txt
ffc_mkdocs_video-1.0.1.dist-info/top_level.txt
ffc_mkdocs_video-1.0.1.dist-info/RECORD
