Metadata-Version: 2.1
Name: ffc-mkdocs-video
Version: 1.0.1
Summary: UNKNOWN
Home-page: https://github.com/cosmos-explorer/ffc-mkdocs-video
Author: Cosmos Explorer
Author-email: lian.yang@gmail.com
License: MIT
Platform: UNKNOWN
Requires-Python: >=3.6
License-File: LICENSE
Requires-Dist: mkdocs (<2,>=1.1.0)
